{
  "version": "6",
  "dialect": "sqlite",
  "id": "5a10d684-57b0-4168-95ab-5db879b64319",
  "prevId": "fb524934-beb0-4bbe-8dd1-4575627d35c9",
  "tables": {
    "inventory": {
      "name": "inventory",
      "columns": {
        "id": {
          "name": "id",
          "type": "integer",
          "primaryKey": true,
          "notNull": true,
          "autoincrement": true
        },
        "batch_id": {
          "name": "batch_id",
          "type": "text",
          "primaryKey": false,
          "notNull": true,
          "autoincrement": false
        },
        "material_id": {
          "name": "material_id",
          "type": "integer",
          "primaryKey": false,
          "notNull": false,
          "autoincrement": false
        },
        "net_weight": {
          "name": "net_weight",
          "type": "real",
          "primaryKey": false,
          "notNull": true,
          "autoincrement": false
        },
        "date": {
          "name": "date",
          "type": "text",
          "primaryKey": false,
          "notNull": true,
          "autoincrement": false
        },
        "status": {
          "name": "status",
          "type": "text",
          "primaryKey": false,
          "notNull": false,
          "autoincrement": false,
          "default": "'In Stock'"
        }
      },
      "indexes": {
        "inventory_batch_id_unique": {
          "name": "inventory_batch_id_unique",
          "columns": [
            "batch_id"
          ],
          "isUnique": true
        }
      },
      "foreignKeys": {
        "inventory_material_id_materials_id_fk": {
          "name": "inventory_material_id_materials_id_fk",
          "tableFrom": "inventory",
          "tableTo": "materials",
          "columnsFrom": [
            "material_id"
          ],
          "columnsTo": [
            "id"
          ],
          "onDelete": "no action",
          "onUpdate": "no action"
        }
      },
      "compositePrimaryKeys": {},
      "uniqueConstraints": {},
      "checkConstraints": {}
    },
    "materials": {
      "name": "materials",
      "columns": {
        "id": {
          "name": "id",
          "type": "integer",
          "primaryKey": true,
          "notNull": true,
          "autoincrement": true
        },
        "name": {
          "name": "name",
          "type": "text",
          "primaryKey": false,
          "notNull": true,
          "autoincrement": false
        },
        "class": {
          "name": "class",
          "type": "text",
          "primaryKey": false,
          "notNull": false,
          "autoincrement": false
        },
        "uom": {
          "name": "uom",
          "type": "text",
          "primaryKey": false,
          "notNull": false,
          "autoincrement": false
        }
      },
      "indexes": {},
      "foreignKeys": {},
      "compositePrimaryKeys": {},
      "uniqueConstraints": {},
      "checkConstraints": {}
    }
  },
  "views": {},
  "enums": {},
  "_meta": {
    "schemas": {},
    "tables": {},
    "columns": {}
  },
  "internal": {
    "indexes": {}
  }
}